markdown_grid_tables/__init__.py
markdown_grid_tables/_version.py
markdown_grid_tables-0.6.0.dist-info/licenses/LICENSE
markdown_grid_tables-0.6.0.dist-info/WHEEL
markdown_grid_tables-0.6.0.dist-info/METADATA
markdown_grid_tables-0.6.0.dist-info/RECORD
